pyuplift/__init__.py
pyuplift/base_model.py
pyuplift/data_processing/__init__.py
pyuplift/data_processing/dummy.py
pyuplift/data_processing/econometric.py
pyuplift/data_processing/two_model.py
pyuplift/datasets/__init__.py
pyuplift/datasets/criteo_uplift_prediction.py
pyuplift/datasets/hillstrom_email_marketing.py
pyuplift/datasets/regression.py
pyuplift/model_selection/__init__.py
pyuplift/model_selection/error_cross_validation.py
pyuplift/model_selection/train_test_split.py
pyuplift/model_selection/treatment_cross_validation.py
pyuplift/utils/__init__.py
pyuplift/utils/downloader.py
pyuplift/utils/retriever.py
pyuplift-0.0.2.9.dist-info/LICENSE
pyuplift-0.0.2.9.dist-info/METADATA
pyuplift-0.0.2.9.dist-info/WHEEL
pyuplift-0.0.2.9.dist-info/top_level.txt
pyuplift-0.0.2.9.dist-info/RECORD
