Metadata-Version: 2.1
Name: pyuplift
Version: 0.0.2.9
Summary: Uplift modeling implementation
Home-page: https://github.com/duketemon/pyuplift
Author: Artem Kuchumov
Author-email: kuchumov7@gmail.com
License: MIT License
Keywords: uplift modeling,machine learning,true-response-modeling,incremental-value-marketing
Platform: UNKNOWN
Classifier: Intended Audience :: Science/Research
Classifier: Intended Audience :: Education
Classifier: Programming Language :: Python :: 3
Classifier: Programming Language :: Python :: 3.6
Classifier: License :: OSI Approved :: MIT License
Classifier: Operating System :: OS Independent
Classifier: Topic :: Software Development :: Libraries
Classifier: Topic :: Software Development :: Libraries :: Python Modules
Requires-Dist: pandas (>=0.23.4)
Requires-Dist: scikit-learn (>=0.20.0)
